{
  "lists":[
    {
      "url":"./detail.html?id=",
      "img":"./static/images/img1.png",
      "name":"李鸿颜",
      "job":"中医医师",
      "desc":"颈椎腰椎，关节炎肩周炎，胃病、肝病和肾病，痛经，心脑血管疾病，疾病预防",
      "detail":"李鸿飞，宫廷御医传人，2010年开创六经八位治疗体系。采用五行辨证法配以独门药方诊治多种疾病，治愈率高。"
    }
  ],
  "detailLists":[
    {
      "img":"./static/images/img1.png",
      "name":"李鸿颜",
      "job":"中医医师",
      "desc":"肩颈腰椎病，关节炎治疗",
      "serviceDesc":"采用祖传秘方治疗肩颈腰椎病。针对各类急慢性关节病有奇效。下单后立即开始诊疗，愈后付款，无效不收取任何额外费用。",
      "detail":"李鸿飞，宫廷御医传人，2010年开创六经八位治疗体系。采用五行辨证法配以独门药方诊治多种疾病，治愈率高。"
    },{
      "img":"./static/images/img1.png",
      "name":"李鸿颜",
      "job":"中医医师",
      "desc":"胃病，肝病肾病，痛经治疗",
      "serviceDesc":"采用五行脏腑辨证配以家传汤剂诊治各种脏腑疾病，如胃病、肝病、肾病及痛经，需要病人未动过相关手术。下单后立即开始诊疗，愈后付款，无效不收取任何额外费用。",
      "detail":"李鸿飞，宫廷御医传人，2010年开创六经八位治疗体系。采用五行辨证法配以独门药方诊治多种疾病，治愈率高。"
    },
    {
      "img":"./static/images/img1.png",
      "name":"李鸿颜",
      "job":"中医医师",
      "desc":"心脑血管病，疾病预防",
      "serviceDesc":"采用六经八位治疗体系诊治各类心脑血管病。独创十二流注经络调理配方能有效增强机体免疫力，预防疾病发生。下单后立即开始诊疗，愈后付款，无效不收取任何额外费用。",
      "detail":"李鸿飞，宫廷御医传人，2010年开创六经八位治疗体系。采用五行辨证法配以独门药方诊治多种疾病，治愈率高。"
    }
  ],
  "details":[
    {
      "img":"./static/images/1.png",
      "name":"王**",
      "num":3,
      "desc":"医生非常耐心！",
      "time":"2017-11-30"
    },
    {
      "img":"./static/images/2.png",
      "name":"周**",
      "num":4,
      "desc":"肩周炎困扰了我12年之久，经过医生的治疗，感觉非常舒服！",
      "time":"2017-11-30"
    },
    {
      "img":"./static/images/3.png",
      "name":"谭**",
      "num":5,
      "desc":"抱着试试的态度来的，真的有效",
      "time":"2017-11-30"
    },
    {
      "img":"./static/images/4.png",
      "name":"李**",
      "num":3,
      "desc":"谢谢医生！",
      "time":"2017-11-30"
    },
    {
      "img":"./static/images/5.png",
      "name":"吴**",
      "num":3,
      "desc":"慢性肝病真的很麻烦，好在治疗几次有了效果",
      "time":"2017-11-30"
    },
    {
      "img":"./static/images/6.png",
      "name":"赵**",
      "num":5,
      "desc":"公司里10个有5个肩颈不舒服，已经推荐给他们了",
      "time":"2017-11-30"
    },
    {
      "img":"./static/images/7.png",
      "name":"包**",
      "num":5,
      "desc":"医生用的药材都很好！",
      "time":"2017-11-30"
    },
    {
      "img":"./static/images/8.png",
      "name":"丁**",
      "num":4,
      "desc":"预约等了挺久，不过有效果也值了",
      "time":"2017-11-30"
    },
    {
      "img":"./static/images/9.png",
      "name":"杨**",
      "num":3,
      "desc":"有没有治疗癌症的医师？急需",
      "time":"2017-11-30"
    },
    {
      "img":"./static/images/10.png",
      "name":"蒋**",
      "num":3,
      "desc":"很有效，都是老中医啊",
      "time":"2017-11-30"
    },
    {
      "img":"./static/images/11.png",
      "name":"孙**",
      "num":3,
      "desc":"暂时控制住了，病情会反复吗？",
      "time":"2017-11-30"
    },
    {
      "img":"./static/images/12.png",
      "name":"王**",
      "num":3,
      "desc":"西医治标，中医治本",
      "time":"2017-11-30"
    },
    {
      "img":"./static/images/13.png",
      "name":"张**",
      "num":5,
      "desc":"感觉不错，哈哈",
      "time":"2017-11-30"
    }
  ]
}



